{
  "type": "Feature",
  "properties": {
    "iso:country":"PR",
    "sg:address":"257 Calle Aduana #145",
    "sg:city":"Mayaguez",
    "sg:classifiers":[
        {
            "category":"Professional",
            "subcategory":"Computer Services",
            "type":"Services"
        }
    ],
    "sg:postcode":"00682",
    "sg:website":"http://140ware.com",
    "wof:name":"140Ware",
    "wof:placetype":"venue"
},
  "geometry": {"coordinates":[-67.1517568,18.2066344],"type":"Point"}
}